luucy/__init__.py
luucy/__version__.py
luucy/base.py
luucy/error.py
luucy/tilesetproxy.py
luucy_python-0.5.0.dist-info/METADATA
luucy_python-0.5.0.dist-info/WHEEL
luucy_python-0.5.0.dist-info/RECORD
